{"created_at": "Sun Oct 16 03:13:40 +0000 2011", "hashtags": [], "id": 125409044222586880, "id_str": "125409044222586880", "lang": "en", "source": "<a href=\"http://ubersocial.com\" rel=\"nofollow\">UberSocial for BlackBerry</a>", "text": "I guess I should go @hublot @apple and @ZegnaOfficial shopping next week. Birthdays only come once a year! Lol", "urls": [], "user": {"created_at": "Sat Apr 09 23:21:29 +0000 2011", "description": "Founder & Principal at Apex Capital Management I am the intersection of Wall Street and Hollywood", "favourites_count": 3973, "followers_count": 746, "friends_count": 848, "geo_enabled": true, "id": 279752245, "id_str": "279752245", "listed_count": 10, "location": "Los Angeles, CA", "name": "Damani", "profile_background_color": "C0DEED", "profile_background_image_url": "http://abs.twimg.com/images/themes/theme1/bg.png", "profile_background_image_url_https": "https://abs.twimg.com/images/themes/theme1/bg.png", "profile_background_tile": true, "profile_banner_url": "https://pbs.twimg.com/profile_banners/279752245/1589464188", "profile_image_url": "http://pbs.twimg.com/profile_images/977291666682912769/FTk6tj6T_normal.jpg", "profile_image_url_https": "https://pbs.twimg.com/profile_images/977291666682912769/FTk6tj6T_normal.jpg", "profile_link_color": "0084B4", "profile_sidebar_border_color": "C0DEED", "profile_sidebar_fill_color": "DDEEF6", "profile_text_color": "333333", "profile_use_background_image": true, "screen_name": "AxeCapitalLLP", "statuses_count": 12861}, "user_mentions": [{"id": 26714575, "id_str": "26714575", "name": "Hublot", "screen_name": "Hublot"}, {"id": 380749300, "id_str": "380749300", "name": "Apple", "screen_name": "Apple"}, {"id": 3031171864, "id_str": "3031171864", "name": "Zegna", "screen_name": "zegnaofficial"}]}