{"created_at": "Mon Oct 17 08:43:29 +0000 2011", "hashtags": [{"text": "Siri"}, {"text": "iPhone4S"}], "id": 125854430171111424, "id_str": "125854430171111424", "lang": "en", "source": "<a href=\"http://www.linkedin.com/\" rel=\"nofollow\">LinkedIn</a>", "text": "#Siri on @Apple #iPhone4S can allow unauthorized access to texts and emails, even when the phone is locked!! http://t.co/0q5dLt22", "urls": [{"expanded_url": "http://lnkd.in/fPscFr", "url": "http://t.co/0q5dLt22"}], "user": {"created_at": "Sat Sep 18 22:15:48 +0000 2010", "description": "Telecom and Technology Analyst with a passion for mobiles and other tech gizmos. Love football and cricket!", "followers_count": 344, "friends_count": 131, "geo_enabled": true, "id": 192351729, "id_str": "192351729", "listed_count": 34, "location": "New Delhi, India", "name": "Katyayan Gupta", "profile_background_color": "ACDED6", "profile_background_image_url": "http://abs.twimg.com/images/themes/theme18/bg.gif", "profile_background_image_url_https": "https://abs.twimg.com/images/themes/theme18/bg.gif", "profile_image_url": "http://pbs.twimg.com/profile_images/2207480973/077_-_Compressed_normal.jpg", "profile_image_url_https": "https://pbs.twimg.com/profile_images/2207480973/077_-_Compressed_normal.jpg", "profile_link_color": "038543", "profile_sidebar_border_color": "EEEEEE", "profile_sidebar_fill_color": "F6F6F6", "profile_text_color": "333333", "profile_use_background_image": true, "screen_name": "Katyayangupta", "statuses_count": 843}, "user_mentions": [{"id": 380749300, "id_str": "380749300", "name": "Apple", "screen_name": "Apple"}]}