{"created_at": "Tue Oct 18 01:19:51 +0000 2011", "favorite_count": 3, "hashtags": [], "id": 126105175294357505, "id_str": "126105175294357505", "lang": "en", "media": [{"display_url": "pic.twitter.com/kubkPO0T", "expanded_url": "https://twitter.com/fredbenenson/status/126105175294357505/photo/1", "id": 126105175298551808, "media_url": "http://pbs.twimg.com/media/AcAD_SICMAANKdy.jpg", "media_url_https": "https://pbs.twimg.com/media/AcAD_SICMAANKdy.jpg", "sizes": {"large": {"h": 960, "resize": "fit", "w": 640}, "medium": {"h": 960, "resize": "fit", "w": 640}, "small": {"h": 680, "resize": "fit", "w": 453}, "thumb": {"h": 150, "resize": "crop", "w": 150}}, "type": "photo", "url": "http://t.co/kubkPO0T"}], "retweet_count": 1, "source": "<a href=\"http://twitter.com/download/iphone\" rel=\"nofollow\">Twitter for iPhone</a>", "text": "Hey @twitter and @apple, this is pretty dumb. http://t.co/kubkPO0T", "urls": [], "user": {"created_at": "Mon Mar 26 04:56:24 +0000 2007", "description": "sourdough & data // https://t.co/NnOkDErBng, Emoji Dick, \ud83e\uddaa, previously @kickstarter, @creativecommons, @ycombinator, surfer, 'not an artist per se' - The Guardian", "favourites_count": 28553, "followers_count": 9397, "friends_count": 3953, "geo_enabled": true, "id": 2254561, "id_str": "2254561", "listed_count": 471, "location": "Los Angeles, CA / NYC", "name": "Maybe: Fred Benenson", "profile_background_color": "000000", "profile_background_image_url": "http://abs.twimg.com/images/themes/theme1/bg.png", "profile_background_image_url_https": "https://abs.twimg.com/images/themes/theme1/bg.png", "profile_banner_url": "https://pbs.twimg.com/profile_banners/2254561/1553019174", "profile_image_url": "http://pbs.twimg.com/profile_images/1245141950459777025/V4SY-Fkm_normal.jpg", "profile_image_url_https": "https://pbs.twimg.com/profile_images/1245141950459777025/V4SY-Fkm_normal.jpg", "profile_link_color": "4A913C", "profile_sidebar_border_color": "87BC44", "profile_sidebar_fill_color": "F2F3FC", "profile_text_color": "000000", "profile_use_background_image": true, "screen_name": "fredbenenson", "statuses_count": 36002, "url": "https://t.co/Iy4u9nK8ES", "verified": true}, "user_mentions": [{"id": 783214, "id_str": "783214", "name": "Twitter", "screen_name": "Twitter"}, {"id": 380749300, "id_str": "380749300", "name": "Apple", "screen_name": "Apple"}]}