{"created_at": "Wed Oct 19 03:03:23 +0000 2011", "hashtags": [{"text": "google"}, {"text": "Nexus"}], "id": 126493616519647232, "id_str": "126493616519647232", "lang": "en", "media": [{"display_url": "pic.twitter.com/CSAeFRHc", "expanded_url": "https://twitter.com/fletchergull/status/126493616519647232/photo/1", "id": 126493616523841537, "media_url": "http://pbs.twimg.com/media/AcFlRidCEAE4_cC.jpg", "media_url_https": "https://pbs.twimg.com/media/AcFlRidCEAE4_cC.jpg", "sizes": {"large": {"h": 399, "resize": "fit", "w": 600}, "medium": {"h": 399, "resize": "fit", "w": 600}, "small": {"h": 399, "resize": "fit", "w": 600}, "thumb": {"h": 150, "resize": "crop", "w": 150}}, "type": "photo", "url": "http://t.co/CSAeFRHc"}], "source": "<a href=\"http://twitter.com/download/iphone\" rel=\"nofollow\">Twitter for iPhone</a>", "text": "Android ice-cream sandwich's \"Face Unlock\" fails to perform recognition when demo'ed on stage :D\n#google #Nexus http://t.co/CSAeFRHc", "urls": [], "user": {"created_at": "Sun Apr 26 20:57:24 +0000 2009", "description": "Not a spare tire...", "favourites_count": 995, "followers_count": 1091, "friends_count": 259, "id": 35562854, "id_str": "35562854", "listed_count": 45, "location": "Tython", "name": "Fletcher", "profile_background_color": "FFFFFF", "profile_background_image_url": "http://abs.twimg.com/images/themes/theme1/bg.png", "profile_background_image_url_https": "https://abs.twimg.com/images/themes/theme1/bg.png", "profile_banner_url": "https://pbs.twimg.com/profile_banners/35562854/1494096784", "profile_image_url": "http://pbs.twimg.com/profile_images/1222626143792238593/a4PJYXtO_normal.jpg", "profile_image_url_https": "https://pbs.twimg.com/profile_images/1222626143792238593/a4PJYXtO_normal.jpg", "profile_link_color": "800080", "profile_sidebar_border_color": "FFFFFF", "profile_sidebar_fill_color": "FFFFFF", "profile_text_color": "800080", "screen_name": "fletchergull", "statuses_count": 57546, "url": "https://t.co/IoYNEZBBUL"}, "user_mentions": []}