{"created_at": "Wed Oct 19 04:39:27 +0000 2011", "hashtags": [{"text": "google"}], "id": 126517793792344064, "id_str": "126517793792344064", "in_reply_to_screen_name": "rohit_bmw", "in_reply_to_status_id": 126517110280171521, "in_reply_to_user_id": 15240491, "lang": "en", "source": "<a href=\"http://twitter.com\" rel=\"nofollow\">Twitter Web Client</a>", "text": "@rohit_bmw Rohit, thanks for being part of my #google+ network!", "urls": [], "user": {"created_at": "Wed Jun 20 20:17:40 +0000 2007", "description": "Inner Architect Principal, digital marketing, blogger & law firm strategist, Blogburst & Plaintiff magazine contributor: https://t.co/Y5Z76pOrqD   Wine is life", "favourites_count": 2237, "followers_count": 5788, "friends_count": 5630, "geo_enabled": true, "id": 6976562, "id_str": "6976562", "listed_count": 283, "location": "San Rafael, CA", "name": "dean guadagni", "profile_background_color": "9AE4E8", "profile_background_image_url": "http://abs.twimg.com/images/themes/theme1/bg.png", "profile_background_image_url_https": "https://abs.twimg.com/images/themes/theme1/bg.png", "profile_banner_url": "https://pbs.twimg.com/profile_banners/6976562/1398794054", "profile_image_url": "http://pbs.twimg.com/profile_images/999321693305819137/gH59ytaW_normal.jpg", "profile_image_url_https": "https://pbs.twimg.com/profile_images/999321693305819137/gH59ytaW_normal.jpg", "profile_link_color": "0084B4", "profile_sidebar_border_color": "BDDCAD", "profile_sidebar_fill_color": "E9DC5D", "profile_text_color": "333333", "profile_use_background_image": true, "screen_name": "deansguide", "statuses_count": 20174, "url": "http://t.co/8VW2LAbH2W"}, "user_mentions": [{"id": 15240491, "id_str": "15240491", "name": "Rohit Gupta", "screen_name": "rohit_bmw"}]}