{"created_at": "Wed Oct 19 03:37:59 +0000 2011", "hashtags": [{"text": "Google"}, {"text": "Samsung"}, {"text": "Android"}], "id": 126502326356815872, "id_str": "126502326356815872", "lang": "en", "source": "<a href=\"http://twitter.com\" rel=\"nofollow\">Twitter Web Client</a>", "text": "RT @tatn: #Google, #Samsung unveil Ice Cream Sandwich-powered Galaxy Nexus http://t.co/uY7KWJiY via @CNET #Android", "urls": [{"expanded_url": "http://cnet.co/psLy7v", "url": "http://t.co/uY7KWJiY"}], "user": {"created_at": "Fri Apr 16 22:46:41 +0000 2010", "description": "Silicon Valley transplant in Pacific NW finally settling down with my partner in life. Mother of two fabulous adult children!", "favourites_count": 154, "followers_count": 469, "friends_count": 454, "geo_enabled": true, "id": 133891207, "id_str": "133891207", "listed_count": 43, "location": "Washington State", "name": "Judy Ajifu", "profile_background_color": "7D6969", "profile_background_image_url": "http://abs.twimg.com/images/themes/theme1/bg.png", "profile_background_image_url_https": "https://abs.twimg.com/images/themes/theme1/bg.png", "profile_banner_url": "https://pbs.twimg.com/profile_banners/133891207/1573487390", "profile_image_url": "http://pbs.twimg.com/profile_images/509727590085455872/JEBPamBz_normal.jpeg", "profile_image_url_https": "https://pbs.twimg.com/profile_images/509727590085455872/JEBPamBz_normal.jpeg", "profile_link_color": "E08686", "profile_sidebar_border_color": "545050", "profile_sidebar_fill_color": "423D3D", "profile_text_color": "965D5E", "profile_use_background_image": true, "screen_name": "JudyAjifu", "statuses_count": 4513, "url": "http://t.co/U6FiM3vs6f"}, "user_mentions": [{"id": 17718867, "id_str": "17718867", "name": "Tuyet T-N.", "screen_name": "tatn"}, {"id": 30261067, "id_str": "30261067", "name": "CNET", "screen_name": "CNET"}]}