{"created_at": "Wed Oct 19 22:39:57 +0000 2011", "hashtags": [{"text": "Microsoft"}, {"text": "PowerPoint"}, {"text": "iPad"}], "id": 126789710705213440, "id_str": "126789710705213440", "lang": "en", "source": "<a href=\"http://twitter.com/download/iphone\" rel=\"nofollow\">Twitter for iPhone</a>", "text": "I wish there was #Microsoft #PowerPoint for #iPad.", "urls": [], "user": {"created_at": "Wed Feb 09 21:13:24 +0000 2011", "description": "###", "favourites_count": 1356, "followers_count": 295, "friends_count": 337, "id": 249820428, "id_str": "249820428", "location": "everywhere", "name": "hopedealer", "profile_background_color": "000000", "profile_background_image_url": "http://abs.twimg.com/images/themes/theme9/bg.gif", "profile_background_image_url_https": "https://abs.twimg.com/images/themes/theme9/bg.gif", "profile_background_tile": true, "profile_banner_url": "https://pbs.twimg.com/profile_banners/249820428/1473484565", "profile_image_url": "http://pbs.twimg.com/profile_images/774476510711472128/vALqRXhl_normal.jpg", "profile_image_url_https": "https://pbs.twimg.com/profile_images/774476510711472128/vALqRXhl_normal.jpg", "profile_link_color": "110000", "profile_sidebar_border_color": "FF0000", "profile_sidebar_fill_color": "2E2E2E", "profile_text_color": "000000", "profile_use_background_image": true, "screen_name": "BigBoost23", "statuses_count": 10611, "url": "https://t.co/qns4YlO3nU"}, "user_mentions": []}