{"created_at": "Wed Oct 19 18:13:47 +0000 2011", "hashtags": [{"text": "Tablet"}, {"text": "Microsoft"}, {"text": "ipad"}, {"text": "productivity"}, {"text": "office"}], "id": 126722729444515840, "id_str": "126722729444515840", "lang": "en", "source": "<a href=\"http://twitter.com\" rel=\"nofollow\">Twitter Web Client</a>", "text": "Windows 8 on a #Tablet? Can #Microsoft put a bruise on the #ipad? - http://t.co/WGRMnyPi #productivity #office", "urls": [{"expanded_url": "http://tabletproductive.com/windows-8-on-a-tablet/", "url": "http://t.co/WGRMnyPi"}], "user": {"created_at": "Wed Jun 29 12:28:09 +0000 2011", "default_profile": true, "description": "Writing about getting more productive through the use of smartphones and tablets. Why carry a paper and pen when you have a tablet and smartphone?", "favourites_count": 262, "followers_count": 1438, "friends_count": 1436, "id": 326127913, "id_str": "326127913", "listed_count": 73, "name": "TabletProductive.com", "profile_background_color": "C0DEED", "profile_background_image_url": "http://abs.twimg.com/images/themes/theme1/bg.png", "profile_background_image_url_https": "https://abs.twimg.com/images/themes/theme1/bg.png", "profile_image_url": "http://pbs.twimg.com/profile_images/813489014909050880/6yg-Cgtc_normal.jpg", "profile_image_url_https": "https://pbs.twimg.com/profile_images/813489014909050880/6yg-Cgtc_normal.jpg", "profile_link_color": "1DA1F2", "profile_sidebar_border_color": "C0DEED", "profile_sidebar_fill_color": "DDEEF6", "profile_text_color": "333333", "profile_use_background_image": true, "screen_name": "tabletproductiv", "statuses_count": 5395, "url": "https://t.co/4fUd6JLtpB"}, "user_mentions": []}