{"created_at": "Thu Oct 20 03:31:56 +0000 2011", "hashtags": [{"text": "Twitter"}], "id": 126863189844566016, "id_str": "126863189844566016", "lang": "pt", "source": "<a href=\"http://twitter.com\" rel=\"nofollow\">Twitter Web Client</a>", "text": "A Dormir.! #Twitter OFF", "urls": [], "user": {"created_at": "Fri May 28 23:02:12 +0000 2010", "description": "23. De los Andes caribe\u00f1os de Sudam\u00e9rica\ud83d\udccd", "favourites_count": 3919, "followers_count": 1106, "friends_count": 289, "geo_enabled": true, "id": 149295713, "id_str": "149295713", "listed_count": 4, "location": "Panam\u00e1", "name": "Ram\u00f3n", "profile_background_color": "050500", "profile_background_image_url": "http://abs.twimg.com/images/themes/theme18/bg.gif", "profile_background_image_url_https": "https://abs.twimg.com/images/themes/theme18/bg.gif", "profile_background_tile": true, "profile_banner_url": "https://pbs.twimg.com/profile_banners/149295713/1454286744", "profile_image_url": "http://pbs.twimg.com/profile_images/1246666699052650496/ykaoEfnX_normal.jpg", "profile_image_url_https": "https://pbs.twimg.com/profile_images/1246666699052650496/ykaoEfnX_normal.jpg", "profile_link_color": "F2D118", "profile_sidebar_border_color": "000000", "profile_sidebar_fill_color": "FCFC24", "profile_text_color": "000000", "profile_use_background_image": true, "screen_name": "Ramonepr_", "statuses_count": 35567}, "user_mentions": []}