{"created_at": "Thu Oct 20 03:24:27 +0000 2011", "hashtags": [{"text": "stupid"}, {"text": "Twitter"}, {"text": "Twitterapp"}, {"text": "mentions"}, {"text": "DRAWLIN"}, {"text": "TMW"}, {"text": "PROMOALLDAY"}, {"text": "FOLLOWLIMITISGAY"}], "id": 126861309185761280, "id_str": "126861309185761280", "lang": "en", "source": "<a href=\"http://twitter.com/download/android\" rel=\"nofollow\">Twitter for Android</a>", "text": "#stupid fucking #Twitter #Twitterapp give me my Damn #mentions NOOWWWWWW!!!!! UGH! #DRAWLIN AS ALWAYS #TMW #PROMOALLDAY #FOLLOWLIMITISGAY TO", "urls": [], "user": {"created_at": "Tue Jun 28 01:23:36 +0000 2011", "description": "a simple twitter bio can't get my message across. \ni just wanna vibe with ya..\ni make music the best i can\ni do business the best i can\ni live the best i can", "favourites_count": 109, "followers_count": 1010, "friends_count": 1385, "id": 325277186, "id_str": "325277186", "listed_count": 16, "location": "PA 717", "name": "Dr. Pimp", "profile_background_color": "000000", "profile_background_image_url": "http://abs.twimg.com/images/themes/theme1/bg.png", "profile_background_image_url_https": "https://abs.twimg.com/images/themes/theme1/bg.png", "profile_banner_url": "https://pbs.twimg.com/profile_banners/325277186/1557090493", "profile_image_url": "http://pbs.twimg.com/profile_images/1125145010914189313/vvt4Jacy_normal.jpg", "profile_image_url_https": "https://pbs.twimg.com/profile_images/1125145010914189313/vvt4Jacy_normal.jpg", "profile_link_color": "000989", "profile_sidebar_border_color": "000000", "profile_sidebar_fill_color": "000000", "profile_text_color": "000000", "screen_name": "SmokeyMcPot717", "statuses_count": 4062}, "user_mentions": []}